kawapack/__init__.py
kawapack/_src/__init__.py
kawapack/_src/image.py
kawapack/_src/unpack.py
kawapack-0.15.3.dist-info/LICENSE
kawapack-0.15.3.dist-info/METADATA
kawapack-0.15.3.dist-info/WHEEL
kawapack-0.15.3.dist-info/RECORD
