Metadata-Version: 2.1
Name: kawapack
Version: 0.15.3
Summary: Utility for extracting Arknights assets
License: AGPL-3.0-or-later
Author: astral4
Author-email: 88992929+astral4@users.noreply.github.com
Requires-Python: >=3.12,<4.0
Classifier: License :: OSI Approved :: GNU Affero General Public License v3 or later (AGPLv3+)
Classifier: Programming Language :: Python :: 3
Requires-Dist: Pillow (>=10.1.0,<11.0.0)
Requires-Dist: UnityPy (>=1.10.6,<2.0.0)
Requires-Dist: fsb5 (>=1.0,<2.0)
Requires-Dist: pycryptodome (>=3.19.0,<4.0.0)
Requires-Dist: pymongo (>=4.5.0,<5.0.0)
